<annotation>
	<folder>data-company-clean</folder>
	<filename>615.jpg</filename>
	<path>/home/numen/Desktop/data-company-clean/615.jpg</path>
	<source>
		<database>Unknown</database>
	</source>
	<size>
		<width>1080</width>
		<height>1920</height>
		<depth>3</depth>
	</size>
	<segmented>0</segmented>
	<object>
		<name>dust collecting barrel</name>
		<pose>Unspecified</pose>
		<truncated>0</truncated>
		<difficult>0</difficult>
		<bndbox>
			<xmin>433</xmin>
			<ymin>461</ymin>
			<xmax>659</xmax>
			<ymax>848</ymax>
		</bndbox>
	</object>
</annotation>
